__init__.py
pylexia.py
experimentals/experimental1.py
inference/models/__init__.py
inference/models/cni.py
learning/models/cni.py
PyLexia-1.19.dist-info/METADATA
PyLexia-1.19.dist-info/WHEEL
PyLexia-1.19.dist-info/top_level.txt
PyLexia-1.19.dist-info/RECORD
