Metadata-Version: 2.1
Name: PyLexia
Version: 1.19
Requires-Dist: numpy
Requires-Dist: cupy-cuda117
Requires-Dist: matplotlib
Requires-Dist: NewlineJSON
Requires-Dist: opencv-python
Requires-Dist: panda
Requires-Dist: pandas-read-xml
Requires-Dist: pdf2image
Requires-Dist: pytesseract
Requires-Dist: spacy
Requires-Dist: tensorflow
